Metadata-Version: 2.3
Name: phone-number-validator-moni13
Version: 0.1.0
Summary: Validate Phone Numbers using NumLookupAPI
Author: Monika Shakya
Author-email: monikashakyaofficial@gmail.com
Requires-Python: >=3.11
Classifier: Programming Language :: Python :: 3
Classifier: Programming Language :: Python :: 3.11
Classifier: Programming Language :: Python :: 3.12
Classifier: Programming Language :: Python :: 3.13
Requires-Dist: requests (>=2.32.4,<3.0.0)
